{"letter":"z","count":76,"entries":[{"id":"zaburi","headword":"zaburi","homonym_index":null,"sort_key":"zaburi","pos":"dzina","pos_en":"noun","noun_class":null,"plural_prefix":"-","plural_form":null,"ipa":"/zaburi/","audio":[],"equivalents_en":["psalm"],"equivalents_sw":["zaburi"],"variants":[],"senses":[{"sense_id":1,"definition_en":"psalm","definition_sw":"zaburi","definition_dg":"","definition_dg_status":"pending","examples":[],"synonyms_dg":[],"antonyms_dg":[],"cross_refs":[],"cultural_note":null,"register":"neutral","dialect_tags":[]}],"etymology":{"source":null,"root":null,"notes":""},"bible_refs":[],"proverb_refs":[],"sub_entries":[],"editorial_state":"draft","is_redirect":false,"redirect_target":null},{"id":"zabwa","headword":"zabwa","homonym_index":null,"sort_key":"zabwa","pos":"dzina","pos_en":"noun","noun_class":null,"plural_prefix":null,"plural_form":null,"ipa":"/zabwa/","audio":[],"equivalents_en":["kusagala to flop down exhausted"],"equivalents_sw":["kuketi kabisa"],"variants":[],"senses":[{"sense_id":1,"definition_en":", kusagala to flop down exhausted","definition_sw":"kuketi kabisa","definition_dg":"Kusagala photsi kpwa uchovu mkpwulu.","definition_dg_status":"draft","examples":[{"dg":"Wazabwa photsi kpwa uchovu bada ya kazi ngumu.","en":"He flopped down exhausted after hard work.","sw":"Aliketi kabisa kwa uchovu baada ya kazi ngumu.","source":"generated"}],"synonyms_dg":[],"antonyms_dg":[],"cross_refs":[],"cultural_note":null,"register":"neutral","dialect_tags":[]}],"etymology":{"source":null,"root":null,"notes":""},"bible_refs":[],"proverb_refs":[],"sub_entries":[],"editorial_state":"draft","is_redirect":false,"redirect_target":null},{"id":"zahabu","headword":"zahabu","homonym_index":null,"sort_key":"zahabu","pos":"dzina","pos_en":"noun","noun_class":null,"plural_prefix":"-","plural_form":null,"ipa":"/zahabu/","audio":[],"equivalents_en":["gold"],"equivalents_sw":["dhahabu"],"variants":[],"senses":[{"sense_id":1,"definition_en":"gold","definition_sw":"dhahabu","definition_dg":"","definition_dg_status":"pending","examples":[],"synonyms_dg":[],"antonyms_dg":[],"cross_refs":[],"cultural_note":null,"register":"neutral","dialect_tags":[]}],"etymology":{"source":null,"root":null,"notes":""},"bible_refs":[],"proverb_refs":[],"sub_entries":[],"editorial_state":"draft","is_redirect":false,"redirect_target":null},{"id":"zaidi","headword":"zaidi","homonym_index":null,"sort_key":"zaidi","pos":"dzina","pos_en":"noun","noun_class":null,"plural_prefix":null,"plural_form":null,"ipa":"/zaid̪i/","audio":[],"equivalents_en":["more"],"equivalents_sw":["zaidi"],"variants":[],"senses":[{"sense_id":1,"definition_en":"more","definition_sw":"zaidi","definition_dg":"","definition_dg_status":"pending","examples":[],"synonyms_dg":[],"antonyms_dg":[],"cross_refs":[],"cultural_note":null,"register":"neutral","dialect_tags":[]}],"etymology":{"source":null,"root":null,"notes":""},"bible_refs":[],"proverb_refs":[],"sub_entries":[],"editorial_state":"draft","is_redirect":false,"redirect_target":null},{"id":"zama","headword":"zama","homonym_index":null,"sort_key":"zama","pos":"chihendo","pos_en":"verb","noun_class":null,"plural_prefix":null,"plural_form":null,"ipa":"/zama/","audio":[],"equivalents_en":["bend over","to sink","to bow down"],"equivalents_sw":["kuzama"],"variants":[],"senses":[{"sense_id":1,"definition_en":"to bend over, to sink, to bow down","definition_sw":"kuzama","definition_dg":"Kuinama photsi, au kuzama kpwenye madzi.","definition_dg_status":"draft","examples":[{"dg":"Dakitari wazama kumlola mkpwongo","en":"The doctor bent over to look at the patient","sw":"Daktari aliinama kumtazama kidonda.","source":"mgombato"},{"dg":"Dziwe rikazama","en":"The stone has sunk","sw":"Daktari aliinama kumtazama kidonda.","source":"mgombato"}],"synonyms_dg":[],"antonyms_dg":[],"cross_refs":[],"cultural_note":null,"register":"neutral","dialect_tags":[]}],"etymology":{"source":null,"root":null,"notes":""},"bible_refs":[],"proverb_refs":[],"sub_entries":[{"id":"zama/zamisa_to","form":"zamisa to","pos":null,"pos_en":null,"definition_en":"bend something","definition_sw":"kuzamisha","definition_dg":"","definition_dg_status":"pending","definition_dg_source":null,"examples":[{"dg":"Anazamisa panda","en":"She is bending the branch","sw":"","source":"mgombato"}],"register":"neutral","dialect_tags":[],"editorial_state":"draft"}],"editorial_state":"draft","is_redirect":false,"redirect_target":null},{"id":"zamani","headword":"zamani","homonym_index":null,"sort_key":"zamani","pos":"dzina","pos_en":"noun","noun_class":null,"plural_prefix":null,"plural_form":null,"ipa":"/zamani/","audio":[],"equivalents_en":["long ago"],"equivalents_sw":["zamani"],"variants":[],"senses":[{"sense_id":1,"definition_en":"long ago","definition_sw":"zamani","definition_dg":"Wakati wa kare sana, zamani.","definition_dg_status":"draft","examples":[{"dg":"Zamani atu kala anaishi kpwa ujanja wa tsakani.","en":"Long ago people lived by the wit of the bush.","sw":"Zamani watu waliishi kwa ujuzi wa porini.","source":"generated"}],"synonyms_dg":[],"antonyms_dg":[],"cross_refs":[],"cultural_note":null,"register":"neutral","dialect_tags":[]}],"etymology":{"source":null,"root":null,"notes":""},"bible_refs":[],"proverb_refs":[],"sub_entries":[],"editorial_state":"draft","is_redirect":false,"redirect_target":null},{"id":"zambalau.1","headword":"zambalau","homonym_index":1,"sort_key":"zambalau","pos":"dzina","pos_en":"noun","noun_class":null,"plural_prefix":null,"plural_form":null,"ipa":"/zaᵐbalau/","audio":[],"equivalents_en":["-ziho"],"equivalents_sw":[],"variants":[],"senses":[{"sense_id":1,"definition_en":"-ziho","definition_sw":"","definition_dg":"","definition_dg_status":"pending","examples":[],"synonyms_dg":[],"antonyms_dg":[],"cross_refs":[],"cultural_note":null,"register":"neutral","dialect_tags":[]}],"etymology":{"source":null,"root":null,"notes":""},"bible_refs":[],"proverb_refs":[],"sub_entries":[{"id":"zambalau/tales_and","form":"tales and","pos":null,"pos_en":null,"definition_en":"children's stories","definition_sw":"hapo zamani","definition_dg":"","definition_dg_status":"pending","definition_dg_source":null,"examples":[],"register":"neutral","dialect_tags":[],"editorial_state":"draft"}],"editorial_state":"draft","is_redirect":false,"redirect_target":null},{"id":"zambalau.2","headword":"zambalau","homonym_index":2,"sort_key":"zambalau","pos":"dzina","pos_en":"noun","noun_class":null,"plural_prefix":null,"plural_form":null,"ipa":"/zaᵐbalau/","audio":[],"equivalents_en":["purple"],"equivalents_sw":["zambarau"],"variants":[],"senses":[{"sense_id":1,"definition_en":"purple","definition_sw":"zambarau","definition_dg":"Rangi ya zambarau, kahi-kahi ya mwekundu na buluu.","definition_dg_status":"draft","examples":[{"dg":"Mchetu wavwala nguwo ya rangi ya zambalau.","en":"The woman wore a purple colored garment.","sw":"Mwanamke alivaa nguo ya rangi ya zambarau.","source":"generated"}],"synonyms_dg":[],"antonyms_dg":[],"cross_refs":[],"cultural_note":null,"register":"neutral","dialect_tags":["Tz"]}],"etymology":{"source":null,"root":null,"notes":""},"bible_refs":[],"proverb_refs":[],"sub_entries":[],"editorial_state":"draft","is_redirect":false,"redirect_target":null},{"id":"zambarau","headword":"zambarau","homonym_index":null,"sort_key":"zambarau","pos":"dzina","pos_en":"noun","noun_class":null,"plural_prefix":null,"plural_form":null,"ipa":"/zaᵐbarau/","audio":[],"equivalents_en":["purple"],"equivalents_sw":["zambarau"],"variants":[],"senses":[{"sense_id":1,"definition_en":"purple","definition_sw":"zambarau","definition_dg":"Rangi ya zambarau, kahi-kahi ya mwekundu na buluu.","definition_dg_status":"draft","examples":[{"dg":"Maua haya gana rangi ya zambarau.","en":"These flowers are purple in color.","sw":"Maua haya yana rangi ya zambarau.","source":"generated"}],"synonyms_dg":[],"antonyms_dg":[],"cross_refs":[],"cultural_note":null,"register":"neutral","dialect_tags":[]}],"etymology":{"source":null,"root":null,"notes":""},"bible_refs":[],"proverb_refs":[],"sub_entries":[],"editorial_state":"draft","is_redirect":false,"redirect_target":null},{"id":"zamiri","headword":"zamiri","homonym_index":null,"sort_key":"zamiri","pos":"chihendo","pos_en":"verb","noun_class":null,"plural_prefix":null,"plural_form":null,"ipa":"/zamiri/","audio":[],"equivalents_en":["intend"],"equivalents_sw":["kudhamiri"],"variants":[],"senses":[{"sense_id":1,"definition_en":"to intend","definition_sw":"kudhamiri","definition_dg":"Kukusudia kuhenda chitu, kuniya.","definition_dg_status":"draft","examples":[{"dg":"Wakazamiri kuhenda vinono kpwenye kazi.","en":"He intended to do well in the work.","sw":"Alidhamiria kufanya vizuri kwenye kazi.","source":"generated"}],"synonyms_dg":[],"antonyms_dg":[],"cross_refs":[],"cultural_note":null,"register":"neutral","dialect_tags":[]}],"etymology":{"source":null,"root":null,"notes":""},"bible_refs":[],"proverb_refs":[],"sub_entries":[],"editorial_state":"draft","is_redirect":false,"redirect_target":null},{"id":"zamisa","headword":"zamisa","homonym_index":null,"sort_key":"zamisa","pos":"chihendo","pos_en":"verb","noun_class":null,"plural_prefix":null,"plural_form":null,"ipa":"","audio":[],"equivalents_en":[],"equivalents_sw":[],"variants":[],"senses":[],"etymology":{"source":null,"root":null,"notes":""},"bible_refs":[],"proverb_refs":[],"sub_entries":[],"editorial_state":"draft","is_redirect":true,"redirect_target":"zama;"},{"id":"zandale","headword":"zandale","homonym_index":null,"sort_key":"zandale","pos":"dzina","pos_en":"noun","noun_class":null,"plural_prefix":"-","plural_form":null,"ipa":"/zaⁿdalɛ/","audio":[],"equivalents_en":["kind of dance"],"equivalents_sw":["aina ya ngoma"],"variants":[],"senses":[{"sense_id":1,"definition_en":"kind of dance","definition_sw":"aina ya ngoma","definition_dg":"Aina ya machezo ga chijadi.","definition_dg_status":"draft","examples":[{"dg":"Achetu ateza zandale kpwenye sherehe.","en":"The women performed the zandale dance at the celebration.","sw":"Wanawake walicheza zandale kwenye sherehe.","source":"generated"}],"synonyms_dg":[],"antonyms_dg":[],"cross_refs":[],"cultural_note":null,"register":"neutral","dialect_tags":[]}],"etymology":{"source":null,"root":null,"notes":""},"bible_refs":[],"proverb_refs":[],"sub_entries":[],"editorial_state":"draft","is_redirect":false,"redirect_target":null},{"id":"zangira","headword":"zangira","homonym_index":null,"sort_key":"zangira","pos":"chihendo","pos_en":"verb","noun_class":null,"plural_prefix":null,"plural_form":null,"ipa":"/zaᵑɡira/","audio":[],"equivalents_en":["surround (only used of people)"],"equivalents_sw":["kuzingira"],"variants":[],"senses":[{"sense_id":1,"definition_en":"to surround (only used of people)","definition_sw":"kuzingira","definition_dg":"Kuzunguka mutu au phatu (kuhusu atu tu).","definition_dg_status":"draft","examples":[{"dg":"Atu amzangira chifu ili asiuke.","en":"People surrounded the chief so he wouldn't leave.","sw":"Watu walimzingira chifu ili asiondoke.","source":"generated"}],"synonyms_dg":[],"antonyms_dg":[],"cross_refs":[],"cultural_note":null,"register":"neutral","dialect_tags":[]}],"etymology":{"source":null,"root":null,"notes":""},"bible_refs":[],"proverb_refs":[],"sub_entries":[],"editorial_state":"draft","is_redirect":false,"redirect_target":null},{"id":"zani","headword":"zani","homonym_index":null,"sort_key":"zani","pos":"dzina","pos_en":"noun","noun_class":null,"plural_prefix":"ma","plural_form":null,"ipa":"/zani/","audio":[],"equivalents_en":["misfortune","calamity","trouble"],"equivalents_sw":["bahati mbaya"],"variants":[],"senses":[{"sense_id":1,"definition_en":"misfortune, calamity, trouble","definition_sw":"bahati mbaya","definition_dg":"Bahati mbii, msiba, taabu.","definition_dg_status":"draft","examples":[{"dg":"Zani ikamgbwira ariphopoteza kazi.","en":"Misfortune struck him when he lost his job.","sw":"Bahati mbaya ilimpata alipopoteza kazi.","source":"generated"}],"synonyms_dg":[],"antonyms_dg":[],"cross_refs":[],"cultural_note":null,"register":"neutral","dialect_tags":[]}],"etymology":{"source":null,"root":null,"notes":""},"bible_refs":[],"proverb_refs":[],"sub_entries":[],"editorial_state":"draft","is_redirect":false,"redirect_target":null},{"id":"zaniya","headword":"zaniya","homonym_index":null,"sort_key":"zaniya","pos":"chihendo","pos_en":"verb","noun_class":null,"plural_prefix":null,"plural_form":null,"ipa":"/zanija/","audio":[],"equivalents_en":["suspect"],"equivalents_sw":["kudhania"],"variants":[],"senses":[{"sense_id":1,"definition_en":"to suspect","definition_sw":"kudhania","definition_dg":"Kudhani, kuona kukala labda ni hivyo.","definition_dg_status":"draft","examples":[{"dg":"Ninazaniya kukala andakpwedza muhondo.","en":"I suspect he will come tomorrow.","sw":"Ninadhani kwamba atakuja kesho.","source":"generated"}],"synonyms_dg":[],"antonyms_dg":[],"cross_refs":[],"cultural_note":null,"register":"neutral","dialect_tags":[]}],"etymology":{"source":null,"root":null,"notes":""},"bible_refs":[],"proverb_refs":[],"sub_entries":[],"editorial_state":"draft","is_redirect":false,"redirect_target":null},{"id":"zarau","headword":"zarau","homonym_index":null,"sort_key":"zarau","pos":"chihendo","pos_en":"verb","noun_class":null,"plural_prefix":null,"plural_form":null,"ipa":"/zarau/","audio":[],"equivalents_en":["scorn","to treat with contempt","to ignore someone"],"equivalents_sw":["kudharau"],"variants":[],"senses":[{"sense_id":1,"definition_en":"to scorn, to treat with contempt, to ignore someone","definition_sw":"kudharau","definition_dg":"Kudharau mutu, kutomuheshimu.","definition_dg_status":"draft","examples":[{"dg":"Usimzarau mutu kpwa sababu ya umaskini.","en":"Don't scorn a person because of poverty.","sw":"Usimdharau mtu kwa sababu ya umaskini.","source":"generated"}],"synonyms_dg":[],"antonyms_dg":[],"cross_refs":[],"cultural_note":null,"register":"neutral","dialect_tags":[]}],"etymology":{"source":null,"root":null,"notes":""},"bible_refs":[],"proverb_refs":[],"sub_entries":[],"editorial_state":"draft","is_redirect":false,"redirect_target":null},{"id":"zarigiza","headword":"zarigiza","homonym_index":null,"sort_key":"zarigiza","pos":"chihendo","pos_en":"verb","noun_class":null,"plural_prefix":null,"plural_form":null,"ipa":"","audio":[],"equivalents_en":[],"equivalents_sw":[],"variants":[],"senses":[],"etymology":{"source":null,"root":null,"notes":""},"bible_refs":[],"proverb_refs":[],"sub_entries":[],"editorial_state":"draft","is_redirect":true,"redirect_target":"dzarigiza;"},{"id":"zawadi","headword":"zawadi","homonym_index":null,"sort_key":"zawadi","pos":"dzina","pos_en":"noun","noun_class":null,"plural_prefix":"-","plural_form":null,"ipa":"/zawad̪i/","audio":[],"equivalents_en":["a gift","a present","a reward"],"equivalents_sw":["zawadi"],"variants":[],"senses":[{"sense_id":1,"definition_en":"a gift, a present, a reward","definition_sw":"zawadi","definition_dg":"Chitu chinahoihwa mutu kpwa furaha au kpwa sababu ya kuhenda vinono.","definition_dg_status":"draft","examples":[{"dg":"Mwanache wahewa zawadi kpwa kufwaulu.","en":"The child was given a gift for succeeding.","sw":"Mtoto alipewa zawadi kwa kufaulu.","source":"generated"}],"synonyms_dg":[],"antonyms_dg":[],"cross_refs":[],"cultural_note":null,"register":"neutral","dialect_tags":[]}],"etymology":{"source":null,"root":null,"notes":""},"bible_refs":[],"proverb_refs":[],"sub_entries":[],"editorial_state":"draft","is_redirect":false,"redirect_target":null},{"id":"zekeya","headword":"zekeya","homonym_index":null,"sort_key":"zekeya","pos":"dzina","pos_en":"noun","noun_class":null,"plural_prefix":null,"plural_form":null,"ipa":"/zɛkɛja/","audio":[],"equivalents_en":["ra chitswa (ma) skull"],"equivalents_sw":["fuvu la kichwa"],"variants":[],"senses":[{"sense_id":1,"definition_en":"ra chitswa (ma) skull","definition_sw":"fuvu la kichwa","definition_dg":"Fuvu ra chitswa, mfupha wa kuezeka ubongo.","definition_dg_status":"draft","examples":[{"dg":"Zekeya ra chitswa ni mfupha muhimu.","en":"The skull is an important bone.","sw":"Fuvu la kichwa ni mfupa muhimu.","source":"generated"}],"synonyms_dg":[],"antonyms_dg":[],"cross_refs":[],"cultural_note":null,"register":"neutral","dialect_tags":[]}],"etymology":{"source":null,"root":null,"notes":""},"bible_refs":[],"proverb_refs":[],"sub_entries":[],"editorial_state":"draft","is_redirect":false,"redirect_target":null},{"id":"zembe","headword":"zembe","homonym_index":null,"sort_key":"zembe","pos":"dzina","pos_en":"noun","noun_class":null,"plural_prefix":"-","plural_form":null,"ipa":"/zɛᵐbɛ/","audio":[],"equivalents_en":["traditional dance involving singing"],"equivalents_sw":[],"variants":[],"senses":[{"sense_id":1,"definition_en":"traditional dance involving singing, clapping and stamping of feet","definition_sw":"","definition_dg":"Machezo ga chijadi ambago ganahumira kuimba, kupiga makofi na kugonga magulu.","definition_dg_status":"draft","examples":[{"dg":"Atu ateza zembe usiku kucha.","en":"People performed the zembe dance all night.","sw":"Watu walicheza zembe usiku kucha.","source":"generated"}],"synonyms_dg":[],"antonyms_dg":[],"cross_refs":[],"cultural_note":null,"register":"neutral","dialect_tags":[]}],"etymology":{"source":null,"root":null,"notes":""},"bible_refs":[],"proverb_refs":[],"sub_entries":[{"id":"zembe/performed_many","form":"performed many","pos":null,"pos_en":null,"definition_en":"days after a funeral","definition_sw":"it is not appropriate for children to attend this dance as it involves mock insults between groups of men","definition_dg":"","definition_dg_status":"pending","definition_dg_source":null,"examples":[],"register":"neutral","dialect_tags":[],"editorial_state":"draft"},{"id":"zembe/and","form":"and","pos":null,"pos_en":null,"definition_en":"women","definition_sw":"ngoma inayoimbwa baada ya matanga; si ngoma nzuri kwa watoto kwa sababu ina matusi","definition_dg":"","definition_dg_status":"pending","definition_dg_source":null,"examples":[],"register":"neutral","dialect_tags":[],"editorial_state":"draft"}],"editorial_state":"draft","is_redirect":false,"redirect_target":null},{"id":"zembuka","headword":"zembuka","homonym_index":null,"sort_key":"zembuka","pos":"chihendo","pos_en":"verb","noun_class":null,"plural_prefix":null,"plural_form":null,"ipa":"/zɛᵐbuka/","audio":[],"equivalents_en":["appear","to be found"],"equivalents_sw":["kutokea","kupatikana"],"variants":[],"senses":[{"sense_id":1,"definition_en":"to appear, to be found","definition_sw":"kutokea, kupatikana","definition_dg":"Kuonekana, kuphahikana, kutokea.","definition_dg_status":"draft","examples":[{"dg":"Mwivi wakazembuka bada ya miaka miiri.","en":"The thief appeared after two years.","sw":"Mwizi alitokea baada ya miaka miwili.","source":"generated"}],"synonyms_dg":[],"antonyms_dg":[],"cross_refs":[],"cultural_note":null,"register":"neutral","dialect_tags":[]}],"etymology":{"source":null,"root":null,"notes":""},"bible_refs":[],"proverb_refs":[],"sub_entries":[],"editorial_state":"draft","is_redirect":false,"redirect_target":null},{"id":"zembula","headword":"zembula","homonym_index":null,"sort_key":"zembula","pos":"chihendo","pos_en":"verb","noun_class":null,"plural_prefix":null,"plural_form":null,"ipa":"/zɛᵐbula/","audio":[],"equivalents_en":["cause to appear","hence: to bring forth","to retrieve","to discover","to invent"],"equivalents_sw":["kufanya kitu kitokee","kwa hiyo: kupeleka","kupata tena","kugundua","kuvumbua","kubuni"],"variants":[],"senses":[{"sense_id":1,"definition_en":"to cause to appear, hence: to bring forth, to retrieve, to discover, to invent","definition_sw":"kufanya kitu kitokee, kwa hiyo: kupeleka, kupata tena, kugundua, kuvumbua, kubuni","definition_dg":"Kuhendesa chitu chionekane, kulavya, kugundua au kuvumbua.","definition_dg_status":"draft","examples":[{"dg":"Wazembula njira nyiphya ya kuhenda kazi.","en":"He discovered a new way of doing work.","sw":"Aligundua njia mpya ya kufanya kazi.","source":"generated"}],"synonyms_dg":[],"antonyms_dg":[],"cross_refs":[],"cultural_note":null,"register":"neutral","dialect_tags":[]}],"etymology":{"source":null,"root":null,"notes":""},"bible_refs":[],"proverb_refs":[],"sub_entries":[],"editorial_state":"draft","is_redirect":false,"redirect_target":null},{"id":"zemeheka","headword":"zemeheka","homonym_index":null,"sort_key":"zemeheka","pos":"chihendo","pos_en":"verb","noun_class":null,"plural_prefix":null,"plural_form":null,"ipa":"/zɛmɛhɛka/","audio":[],"equivalents_en":["wander about aimlessly"],"equivalents_sw":["kuzunguka"],"variants":[],"senses":[{"sense_id":1,"definition_en":"to wander about aimlessly","definition_sw":"kuzunguka","definition_dg":"Kuzurura bila sababu, kuangaika.","definition_dg_status":"draft","examples":[{"dg":"Usizemeheke, phiya kaya ukahende kazi.","en":"Don't wander about aimlessly, go home and do work.","sw":"Usizunguke bure, nenda nyumbani ukafanye kazi.","source":"generated"}],"synonyms_dg":[],"antonyms_dg":[],"cross_refs":[],"cultural_note":null,"register":"neutral","dialect_tags":[]}],"etymology":{"source":null,"root":null,"notes":""},"bible_refs":[],"proverb_refs":[],"sub_entries":[],"editorial_state":"draft","is_redirect":false,"redirect_target":null},{"id":"zemerera","headword":"zemerera","homonym_index":null,"sort_key":"zemerera","pos":"chihendo","pos_en":"verb","noun_class":null,"plural_prefix":null,"plural_form":null,"ipa":"/zɛmɛrɛra/","audio":[],"equivalents_en":["taunt","to boo"],"equivalents_sw":["kuzomea"],"variants":[],"senses":[{"sense_id":1,"definition_en":"to taunt, to boo","definition_sw":"kuzomea","definition_dg":"Kumzomea mutu, kumbera.","definition_dg_status":"draft","examples":[{"dg":"Atu amzemerera ariphoigbwa.","en":"People taunted him when he lost.","sw":"Watu walimzomea aliposhindwa.","source":"generated"}],"synonyms_dg":[],"antonyms_dg":[],"cross_refs":[],"cultural_note":null,"register":"neutral","dialect_tags":[]}],"etymology":{"source":null,"root":null,"notes":""},"bible_refs":[],"proverb_refs":[],"sub_entries":[],"editorial_state":"draft","is_redirect":false,"redirect_target":null},{"id":"zengula","headword":"zengula","homonym_index":null,"sort_key":"zengula","pos":"chihendo","pos_en":"verb","noun_class":null,"plural_prefix":null,"plural_form":null,"ipa":"","audio":[],"equivalents_en":[],"equivalents_sw":[],"variants":[],"senses":[],"etymology":{"source":null,"root":null,"notes":""},"bible_refs":[],"proverb_refs":[],"sub_entries":[],"editorial_state":"draft","is_redirect":true,"redirect_target":"zenguwa;"},{"id":"zenguwa","headword":"zenguwa","homonym_index":null,"sort_key":"zenguwa","pos":"chihendo","pos_en":"verb","noun_class":null,"plural_prefix":null,"plural_form":null,"ipa":"/zɛᵑɡuwa/","audio":[],"equivalents_en":["free someone from an evil spell by performing a ceremony in which Qur'anic verses are read and the person may be showered with"],"equivalents_sw":[],"variants":[],"senses":[{"sense_id":1,"definition_en":"to free someone from an evil spell by performing a ceremony in which Qur'anic verses are read and the person may be showered with","definition_sw":"","definition_dg":"Kumutuluza mutu kula kpwenye uchawi kpwa kusoma aya za Qurani na kumwosha.","definition_dg_status":"draft","examples":[{"dg":"Mganga wamuzenguwa mgonjwa kpwa aya za Qurani.","en":"The healer freed the patient from an evil spell using Quranic verses.","sw":"Mganga alimponya mgonjwa kwa aya za Qurani.","source":"generated"}],"synonyms_dg":[],"antonyms_dg":[],"cross_refs":[],"cultural_note":null,"register":"neutral","dialect_tags":[]}],"etymology":{"source":null,"root":null,"notes":""},"bible_refs":[],"proverb_refs":[],"sub_entries":[{"id":"zenguwa/dry_rice","form":"dry rice","pos":null,"pos_en":null,"definition_en":"or beans to symbolise washing","definition_sw":"also used of the same actions being performed in a service of thanksgiving for healing or escape from danger; kuzingua","definition_dg":"","definition_dg_status":"pending","definition_dg_source":null,"examples":[],"register":"neutral","dialect_tags":[],"editorial_state":"draft"}],"editorial_state":"draft","is_redirect":false,"redirect_target":null},{"id":"zewe","headword":"zewe","homonym_index":null,"sort_key":"zewe","pos":"dzina","pos_en":"noun","noun_class":null,"plural_prefix":"-","plural_form":null,"ipa":"/zɛwɛ/","audio":[],"equivalents_en":["loot","booty"],"equivalents_sw":["nyara"],"variants":[],"senses":[{"sense_id":1,"definition_en":"loot, booty","definition_sw":"nyara","definition_dg":"Vitu virivyoiywa kpwa nguvu, nyara.","definition_dg_status":"draft","examples":[{"dg":"Asikari ahala zewe kula kpwa adui.","en":"Soldiers took loot from the enemy.","sw":"Askari walichukua nyara kutoka kwa adui.","source":"generated"}],"synonyms_dg":[],"antonyms_dg":[],"cross_refs":[],"cultural_note":null,"register":"neutral","dialect_tags":[]}],"etymology":{"source":null,"root":null,"notes":""},"bible_refs":[],"proverb_refs":[],"sub_entries":[],"editorial_state":"draft","is_redirect":false,"redirect_target":null},{"id":"zh","headword":"zh","homonym_index":null,"sort_key":"zh","pos":"dzina","pos_en":"noun","noun_class":null,"plural_prefix":null,"plural_form":null,"ipa":"/zh/","audio":[],"equivalents_en":["this is the voiced counterpart of sh and occurs in a very few words"],"equivalents_sw":[],"variants":[],"senses":[{"sense_id":1,"definition_en":"this is the voiced counterpart of sh and occurs in a very few words, probably of Giryama origin (e.g. chitindizho ‘cattle pen’). As well as sounds that are different, some of the letter combinations used in Digo are","definition_sw":"","definition_dg":"Harufu ya Chidigo ambayo ni sauti ya sh ela kpwa sauti kulu. Inaonekana kpwenye maneno machache, labda ya asili ya Chigiryama.","definition_dg_status":"draft","examples":[{"dg":"'Chitindizho' rina harufu zh ambayo si ya kawaida kpwenye Chidigo.","en":"'Chitindizho' has the zh sound which is uncommon in Digo.","sw":"'Chitindizho' lina sauti zh ambayo si ya kawaida katika Kidigo.","source":"generated"}],"synonyms_dg":[],"antonyms_dg":[],"cross_refs":[],"cultural_note":null,"register":"neutral","dialect_tags":[]}],"etymology":{"source":null,"root":null,"notes":""},"bible_refs":[],"proverb_refs":[],"sub_entries":[],"editorial_state":"draft","is_redirect":false,"redirect_target":null},{"id":"ziba","headword":"ziba","homonym_index":null,"sort_key":"ziba","pos":"chihendo","pos_en":"verb","noun_class":null,"plural_prefix":null,"plural_form":null,"ipa":"/ziba/","audio":[],"equivalents_en":["cover","to block"],"equivalents_sw":["kuziba"],"variants":[],"senses":[{"sense_id":1,"definition_en":"to cover, to block","definition_sw":"kuziba","definition_dg":"Kufunikira tundu, kuzuwiya chitu chisitsupire.","definition_dg_status":"draft","examples":[{"dg":"Ziba tundu ra ukuta ili panya asiinjire.","en":"Block the hole in the wall so mice don't enter.","sw":"Ziba tundu la ukuta ili panya wasiingie.","source":"generated"}],"synonyms_dg":[],"antonyms_dg":[],"cross_refs":[],"cultural_note":null,"register":"neutral","dialect_tags":[]}],"etymology":{"source":null,"root":null,"notes":""},"bible_refs":[],"proverb_refs":[],"sub_entries":[],"editorial_state":"draft","is_redirect":false,"redirect_target":null},{"id":"zidi","headword":"zidi","homonym_index":null,"sort_key":"zidi","pos":"chihendo","pos_en":"verb","noun_class":null,"plural_prefix":null,"plural_form":null,"ipa":"/zid̪i/","audio":[],"equivalents_en":["increase"],"equivalents_sw":["kuzidi"],"variants":[],"senses":[{"sense_id":1,"definition_en":"to increase, to keep on (doing something)","definition_sw":"kuzidi","definition_dg":"Kuenderera kuhenda chitu, kuendelea zaidi.","definition_dg_status":"draft","examples":[{"dg":"Zidi kuhenda kazi vinono.","en":"Keep on doing work well.","sw":"Zidi kufanya kazi vizuri.","source":"generated"}],"synonyms_dg":[],"antonyms_dg":[],"cross_refs":[],"cultural_note":null,"register":"neutral","dialect_tags":[]}],"etymology":{"source":null,"root":null,"notes":""},"bible_refs":[],"proverb_refs":[],"sub_entries":[],"editorial_state":"draft","is_redirect":false,"redirect_target":null},{"id":"zidisha","headword":"zidisha","homonym_index":null,"sort_key":"zidisha","pos":"chihendo","pos_en":"verb","noun_class":null,"plural_prefix":null,"plural_form":null,"ipa":"/zid̪iʃa/","audio":[],"equivalents_en":["multiply","to add more","to increase"],"equivalents_sw":["kuongeza","kuzidisha"],"variants":[],"senses":[{"sense_id":1,"definition_en":"to multiply, to add more, to increase","definition_sw":"kuongeza, kuzidisha","definition_dg":"Kuongeza chitu, kuhendesa chitu chikale chinji zaidi.","definition_dg_status":"draft","examples":[{"dg":"Zidisha juhudi zako ili ufwaulu.","en":"Increase your efforts so you succeed.","sw":"Zidisha juhudi zako ili ufaulu.","source":"generated"}],"synonyms_dg":[],"antonyms_dg":[],"cross_refs":[],"cultural_note":null,"register":"neutral","dialect_tags":[]}],"etymology":{"source":null,"root":null,"notes":""},"bible_refs":[],"proverb_refs":[],"sub_entries":[],"editorial_state":"draft","is_redirect":false,"redirect_target":null},{"id":"ziga","headword":"ziga","homonym_index":null,"sort_key":"ziga","pos":"chihendo","pos_en":"verb","noun_class":null,"plural_prefix":null,"plural_form":null,"ipa":"/ziɡa/","audio":[],"equivalents_en":["slander","to gossip"],"equivalents_sw":["kusingizia","kusengenya","kukashifu"],"variants":[],"senses":[{"sense_id":1,"definition_en":"to slander, to gossip, to tell a lie in order to get something","definition_sw":"kusingizia, kusengenya, kukashifu","definition_dg":"Kugomba maneno mabii kuhusu mutu ili atu amzire, kusingizia.","definition_dg_status":"draft","examples":[{"dg":"Usimzige mutu, ni kosa.","en":"Don't slander a person, it is wrong.","sw":"Usimsingizie mtu, ni kosa.","source":"generated"}],"synonyms_dg":[],"antonyms_dg":[],"cross_refs":[],"cultural_note":null,"register":"neutral","dialect_tags":[]}],"etymology":{"source":null,"root":null,"notes":""},"bible_refs":[],"proverb_refs":[],"sub_entries":[],"editorial_state":"draft","is_redirect":false,"redirect_target":null},{"id":"ziho","headword":"-ziho","homonym_index":null,"sort_key":"ziho","pos":"sifa","pos_en":"adjective","noun_class":null,"plural_prefix":null,"plural_form":null,"ipa":"/zihɔ/","audio":[],"equivalents_en":["heavy","thick"],"equivalents_sw":["-zito"],"variants":[],"senses":[{"sense_id":1,"definition_en":"heavy, thick","definition_sw":"-zito","definition_dg":"Chenye uzito, nziho, isiyo nafyuhe.","definition_dg_status":"draft","examples":[{"dg":"Chitabu chiziho chi dzulu ya meza ndziho","en":"A","sw":"Kitabu kizito kiko juu ya meza nzito.","source":"mgombato"}],"synonyms_dg":[],"antonyms_dg":[],"cross_refs":[],"cultural_note":null,"register":"neutral","dialect_tags":[]}],"etymology":{"source":null,"root":null,"notes":""},"bible_refs":[],"proverb_refs":[],"sub_entries":[],"editorial_state":"draft","is_redirect":false,"redirect_target":null},{"id":"zii.1","headword":"zii","homonym_index":1,"sort_key":"zii","pos":"dzina","pos_en":"noun","noun_class":null,"plural_prefix":null,"plural_form":null,"ipa":"/zii/","audio":[],"equivalents_en":["zuguza thick"],"equivalents_sw":[],"variants":[],"senses":[{"sense_id":1,"definition_en":"zuguza thick, heavy book is on the heavy table","definition_sw":"","definition_dg":"Kpwa kimya, bila sauti yoyosi.","definition_dg_status":"draft","examples":[{"dg":"Hinyo atu ariphomsikira, azidi kunyamala zii.","en":"When those people heard him, they remained completely silent.","sw":"Watu hao walipomsikia, walizidi kunyamala kimya.","source":"generated"}],"synonyms_dg":[],"antonyms_dg":[],"cross_refs":[],"cultural_note":null,"register":"neutral","dialect_tags":[]}],"etymology":{"source":null,"root":null,"notes":""},"bible_refs":[],"proverb_refs":[],"sub_entries":[],"editorial_state":"draft","is_redirect":false,"redirect_target":null},{"id":"zii.1","headword":"zii","homonym_index":1,"sort_key":"zii","pos":"dzina","pos_en":"noun","noun_class":null,"plural_prefix":null,"plural_form":null,"ipa":"/zii/","audio":[],"equivalents_en":["silently"],"equivalents_sw":["kimya"],"variants":[],"senses":[{"sense_id":1,"definition_en":"silently","definition_sw":"kimya","definition_dg":"Kpwa kimya, bila sauti yoyosi.","definition_dg_status":"draft","examples":[{"dg":"Hinyo atu ariphomsikira anagomba chikpwao, azidi kunyamala zii","en":"When those people heard him talking thier own language, they became completely silent","sw":"Watu hao walipomsikia, walizidi kunyamala kimya.","source":"mgombato"}],"synonyms_dg":[],"antonyms_dg":[],"cross_refs":[],"cultural_note":null,"register":"neutral","dialect_tags":[]},{"sense_id":2,"definition_en":"calm, still (weather)","definition_sw":"shwari, -tulivu","definition_dg":"Hali ya kutokuwa na upepo, shwari.","definition_dg_status":"draft","examples":[{"dg":"Ku zii","en":"It (the weather) is calm","sw":"Kuna shwari, hakuna upepo wowote.","source":"mgombato"}],"synonyms_dg":[],"antonyms_dg":[],"cross_refs":[],"cultural_note":null,"register":"neutral","dialect_tags":[]}],"etymology":{"source":null,"root":null,"notes":""},"bible_refs":[],"proverb_refs":[],"sub_entries":[],"editorial_state":"draft","is_redirect":false,"redirect_target":null},{"id":"zii.2","headword":"zii","homonym_index":2,"sort_key":"zii","pos":"dzina","pos_en":"noun","noun_class":null,"plural_prefix":null,"plural_form":null,"ipa":"/zii/","audio":[],"equivalents_en":["very cold","chilly (water)"],"equivalents_sw":["-a baridi (hasa maji)"],"variants":[],"senses":[{"sense_id":1,"definition_en":"very cold, chilly (water)","definition_sw":"-a baridi (hasa maji)","definition_dg":"Baridi sana (kuhusu madzi tu).","definition_dg_status":"draft","examples":[{"dg":"Madzi ga zii","en":"Very cold water","sw":"Maji ni baridi sana, hatuwezi kuogea nayo.","source":"mgombato"}],"synonyms_dg":[],"antonyms_dg":[],"cross_refs":[],"cultural_note":null,"register":"neutral","dialect_tags":[]}],"etymology":{"source":null,"root":null,"notes":""},"bible_refs":[],"proverb_refs":[],"sub_entries":[],"editorial_state":"draft","is_redirect":false,"redirect_target":null},{"id":"zika","headword":"zika","homonym_index":null,"sort_key":"zika","pos":"chihendo","pos_en":"verb","noun_class":null,"plural_prefix":null,"plural_form":null,"ipa":"/zika/","audio":[],"equivalents_en":["bury (formal process)"],"equivalents_sw":["kuzika"],"variants":[],"senses":[{"sense_id":1,"definition_en":"to bury (formal process)","definition_sw":"kuzika","definition_dg":"Kuika mwiri wa mutu ariyefwa kpwenye tsongo, kuzika.","definition_dg_status":"draft","examples":[{"dg":"Mazishi gahendwa dziloni.","en":"The burial was held in the evening.","sw":"Mazishi yalifanywa jioni.","source":"generated"}],"synonyms_dg":[],"antonyms_dg":[],"cross_refs":[],"cultural_note":null,"register":"neutral","dialect_tags":[]}],"etymology":{"source":null,"root":null,"notes":""},"bible_refs":[],"proverb_refs":[],"sub_entries":[],"editorial_state":"draft","is_redirect":false,"redirect_target":null},{"id":"ziki","headword":"ziki","homonym_index":null,"sort_key":"ziki","pos":"dzina","pos_en":"noun","noun_class":null,"plural_prefix":"-","plural_form":null,"ipa":"/ziki/","audio":[],"equivalents_en":["trouble"],"equivalents_sw":["dhiki"],"variants":[],"senses":[{"sense_id":1,"definition_en":"trouble","definition_sw":"dhiki","definition_dg":"Taabu, shida, hali ngumu.","definition_dg_status":"draft","examples":[{"dg":"Ana ziki kulu kpwa sababu ya ukosefu wa kazi.","en":"He is in great trouble because of lack of work.","sw":"Ana dhiki kubwa kwa sababu ya ukosefu wa kazi.","source":"generated"}],"synonyms_dg":[],"antonyms_dg":[],"cross_refs":[],"cultural_note":null,"register":"neutral","dialect_tags":[]}],"etymology":{"source":null,"root":null,"notes":""},"bible_refs":[],"proverb_refs":[],"sub_entries":[],"editorial_state":"draft","is_redirect":false,"redirect_target":null},{"id":"zikiri","headword":"zikiri","homonym_index":null,"sort_key":"zikiri","pos":"dzina","pos_en":"noun","noun_class":null,"plural_prefix":"-","plural_form":null,"ipa":"/zikiri/","audio":[],"equivalents_en":["see dhikiri"],"equivalents_sw":["angalia dhikiri"],"variants":[],"senses":[{"sense_id":1,"definition_en":"see dhikiri","definition_sw":"angalia dhikiri","definition_dg":"Angaliya dhikiri.","definition_dg_status":"draft","examples":[{"dg":"Zikiri ni neno ranjine ra dhikiri.","en":"Zikiri is another word for dhikiri.","sw":"Zikiri ni neno jingine la dhikiri.","source":"generated"}],"synonyms_dg":[],"antonyms_dg":[],"cross_refs":[],"cultural_note":null,"register":"neutral","dialect_tags":[]}],"etymology":{"source":null,"root":null,"notes":""},"bible_refs":[],"proverb_refs":[],"sub_entries":[],"editorial_state":"draft","is_redirect":false,"redirect_target":null},{"id":"zima","headword":"-zima","homonym_index":null,"sort_key":"zima","pos":"sifa","pos_en":"adjective","noun_class":null,"plural_prefix":null,"plural_form":null,"ipa":"/zima/","audio":[],"equivalents_en":["whole","well","healthy","alive"],"equivalents_sw":["-zima"],"variants":[],"senses":[{"sense_id":1,"definition_en":"whole, well, healthy, alive","definition_sw":"-zima","definition_dg":"Yosi, yenye kukala hai, yenye afya ndzuri.","definition_dg_status":"draft","examples":[{"dg":"Mwanache a zima, ana afya ndzuri.","en":"The child is healthy, he is in good health.","sw":"Mtoto ni mzima, ana afya nzuri.","source":"generated"}],"synonyms_dg":[],"antonyms_dg":[],"cross_refs":[],"cultural_note":null,"register":"neutral","dialect_tags":[]}],"etymology":{"source":null,"root":null,"notes":""},"bible_refs":[],"proverb_refs":[],"sub_entries":[],"editorial_state":"draft","is_redirect":false,"redirect_target":null},{"id":"zimiya","headword":"zimiya","homonym_index":null,"sort_key":"zimiya","pos":"chihendo","pos_en":"verb","noun_class":null,"plural_prefix":null,"plural_form":null,"ipa":"/zimija/","audio":[],"equivalents_en":["faint"],"equivalents_sw":["kuzimia"],"variants":[],"senses":[{"sense_id":1,"definition_en":"to faint","definition_sw":"kuzimia","definition_dg":"Kupoteza fahamu kpwa muda mfupi, kuzimia.","definition_dg_status":"draft","examples":[{"dg":"Wazimiya kpwa sababu ya joto kulu.","en":"He fainted because of the great heat.","sw":"Alizimia kwa sababu ya joto kali.","source":"generated"}],"synonyms_dg":[],"antonyms_dg":[],"cross_refs":[],"cultural_note":null,"register":"neutral","dialect_tags":[]}],"etymology":{"source":null,"root":null,"notes":""},"bible_refs":[],"proverb_refs":[],"sub_entries":[],"editorial_state":"draft","is_redirect":false,"redirect_target":null},{"id":"zimu","headword":"zimu","homonym_index":null,"sort_key":"zimu","pos":"dzina","pos_en":"noun","noun_class":null,"plural_prefix":"ma","plural_form":null,"ipa":"/zimu/","audio":[],"equivalents_en":["ghost"],"equivalents_sw":["zimu"],"variants":[],"senses":[{"sense_id":1,"definition_en":"ghost","definition_sw":"zimu","definition_dg":"","definition_dg_status":"pending","examples":[],"synonyms_dg":[],"antonyms_dg":[],"cross_refs":[],"cultural_note":null,"register":"neutral","dialect_tags":[]}],"etymology":{"source":null,"root":null,"notes":""},"bible_refs":[],"proverb_refs":[],"sub_entries":[],"editorial_state":"draft","is_redirect":false,"redirect_target":null},{"id":"zimya","headword":"zimya","homonym_index":null,"sort_key":"zimya","pos":"chihendo","pos_en":"verb","noun_class":null,"plural_prefix":null,"plural_form":null,"ipa":"/zimja/","audio":[],"equivalents_en":["extinguish","to put out","to switch off"],"equivalents_sw":["kuzima"],"variants":[],"senses":[{"sense_id":1,"definition_en":"to extinguish, to put out, to switch off","definition_sw":"kuzima","definition_dg":"Kuusa moho au mwanga, kuzima.","definition_dg_status":"draft","examples":[{"dg":"Zimya taa kabila ya kulala.","en":"Switch off the light before sleeping.","sw":"Zima taa kabla ya kulala.","source":"generated"}],"synonyms_dg":[],"antonyms_dg":[],"cross_refs":[],"cultural_note":null,"register":"neutral","dialect_tags":[]}],"etymology":{"source":null,"root":null,"notes":""},"bible_refs":[],"proverb_refs":[],"sub_entries":[],"editorial_state":"draft","is_redirect":false,"redirect_target":null},{"id":"zinga","headword":"zinga","homonym_index":null,"sort_key":"zinga","pos":"chihendo","pos_en":"verb","noun_class":null,"plural_prefix":null,"plural_form":null,"ipa":"/ziᵑɡa/","audio":[],"equivalents_en":["commit adultery"],"equivalents_sw":["kuzinzi"],"variants":[],"senses":[{"sense_id":1,"definition_en":"to commit adultery","definition_sw":"kuzinzi","definition_dg":"Kusagala na mutu asiye mchumba wako, kuzini.","definition_dg_status":"draft","examples":[{"dg":"Kuzinga ni kosa kpwa shariya na mila.","en":"Committing adultery is a crime by law and custom.","sw":"Kuzini ni kosa kisheria na kimila.","source":"generated"}],"synonyms_dg":[],"antonyms_dg":[],"cross_refs":[],"cultural_note":null,"register":"neutral","dialect_tags":[]}],"etymology":{"source":null,"root":null,"notes":""},"bible_refs":[],"proverb_refs":[],"sub_entries":[],"editorial_state":"draft","is_redirect":false,"redirect_target":null},{"id":"zini","headword":"zini","homonym_index":null,"sort_key":"zini","pos":"chihendo","pos_en":"verb","noun_class":null,"plural_prefix":null,"plural_form":null,"ipa":"/zini/","audio":[],"equivalents_en":["commit adultery","to fornicate"],"equivalents_sw":["kuzini"],"variants":[],"senses":[{"sense_id":1,"definition_en":"to commit adultery, to fornicate","definition_sw":"kuzini","definition_dg":"Kuzini, kusagala na mutu asiye mchumba wako.","definition_dg_status":"draft","examples":[{"dg":"Kuzini ni dzambo bii kpwa mila na dini.","en":"Fornication is a bad thing in culture and religion.","sw":"Kuzini ni jambo baya katika mila na dini.","source":"generated"}],"synonyms_dg":[],"antonyms_dg":[],"cross_refs":[],"cultural_note":null,"register":"neutral","dialect_tags":[]}],"etymology":{"source":null,"root":null,"notes":""},"bible_refs":[],"proverb_refs":[],"sub_entries":[],"editorial_state":"draft","is_redirect":false,"redirect_target":null},{"id":"zinje","headword":"zinje","homonym_index":null,"sort_key":"zinje","pos":"dzina","pos_en":"noun","noun_class":null,"plural_prefix":null,"plural_form":null,"ipa":"/ziⁿʤɛ/","audio":[],"equivalents_en":["mist"],"equivalents_sw":["ukungu"],"variants":[],"senses":[{"sense_id":1,"definition_en":"mist","definition_sw":"ukungu","definition_dg":"","definition_dg_status":"pending","examples":[{"dg":"Dzana mwezi wakala na zinje","en":"Last night the moon was obscured by mist","sw":"","source":"mgombato"}],"synonyms_dg":[],"antonyms_dg":[],"cross_refs":[],"cultural_note":null,"register":"neutral","dialect_tags":[]}],"etymology":{"source":null,"root":null,"notes":""},"bible_refs":[],"proverb_refs":[],"sub_entries":[],"editorial_state":"draft","is_redirect":false,"redirect_target":null},{"id":"zira","headword":"zira","homonym_index":null,"sort_key":"zira","pos":"chihendo","pos_en":"verb","noun_class":null,"plural_prefix":null,"plural_form":null,"ipa":"/zira/","audio":[],"equivalents_en":["hate","to resent","to dislike"],"equivalents_sw":["kuchukia"],"variants":[],"senses":[{"sense_id":1,"definition_en":"to hate, to resent, to dislike","definition_sw":"kuchukia","definition_dg":"Kutomendza mutu au chitu, kuchukia.","definition_dg_status":"draft","examples":[{"dg":"Usimzire mutu kpwa sababu ya makosa gakege.","en":"Don't hate a person because of their mistakes.","sw":"Usimchukie mtu kwa sababu ya makosa yake.","source":"generated"}],"synonyms_dg":[],"antonyms_dg":[],"cross_refs":[],"cultural_note":null,"register":"neutral","dialect_tags":[]}],"etymology":{"source":null,"root":null,"notes":""},"bible_refs":[],"proverb_refs":[],"sub_entries":[],"editorial_state":"draft","is_redirect":false,"redirect_target":null},{"id":"zirimika","headword":"zirimika","homonym_index":null,"sort_key":"zirimika","pos":"chihendo","pos_en":"verb","noun_class":null,"plural_prefix":null,"plural_form":null,"ipa":"/zirimika/","audio":[],"equivalents_en":["disappear from sight by being covered up"],"equivalents_sw":["kutoweka"],"variants":[],"senses":[{"sense_id":1,"definition_en":"to disappear from sight by being covered up","definition_sw":"kutoweka","definition_dg":"Kutoonekana kpwa kufunikpwa au kudzifwitsa.","definition_dg_status":"draft","examples":[{"dg":"Nyoka ikazirimika kpwenye nyasi.","en":"The snake disappeared into the grass.","sw":"Nyoka ilitoweka kwenye nyasi.","source":"generated"}],"synonyms_dg":[],"antonyms_dg":[],"cross_refs":[],"cultural_note":null,"register":"neutral","dialect_tags":[]}],"etymology":{"source":null,"root":null,"notes":""},"bible_refs":[],"proverb_refs":[],"sub_entries":[],"editorial_state":"draft","is_redirect":false,"redirect_target":null},{"id":"ziya","headword":"ziya","homonym_index":null,"sort_key":"ziya","pos":"dzina","pos_en":"noun","noun_class":null,"plural_prefix":"ma","plural_form":null,"ipa":"/zija/","audio":[],"equivalents_en":["lake"],"equivalents_sw":["ziwa"],"variants":[],"senses":[{"sense_id":1,"definition_en":"lake","definition_sw":"ziwa","definition_dg":"","definition_dg_status":"pending","examples":[],"synonyms_dg":[],"antonyms_dg":[],"cross_refs":[],"cultural_note":null,"register":"neutral","dialect_tags":[]}],"etymology":{"source":null,"root":null,"notes":""},"bible_refs":[],"proverb_refs":[],"sub_entries":[],"editorial_state":"draft","is_redirect":false,"redirect_target":null},{"id":"ziza","headword":"ziza","homonym_index":null,"sort_key":"ziza","pos":"chihendo","pos_en":"verb","noun_class":null,"plural_prefix":null,"plural_form":null,"ipa":"/ziza/","audio":[],"equivalents_en":["wean (a child)"],"equivalents_sw":["kuatisha","kuwachisha mtoto kunyonya"],"variants":[],"senses":[{"sense_id":1,"definition_en":"to wean (a child)","definition_sw":"kuatisha, kuwachisha mtoto kunyonya","definition_dg":"Kuachisha mwanache kushuma, kumwika mwanache chakurya badala ya maziwa.","definition_dg_status":"draft","examples":[{"dg":"Mayo wamziza mwanawe ariphofika miezi kumi na miiri.","en":"Mother weaned her child when he reached twelve months.","sw":"Mama alimwachisha kunyonya mtoto wake alipofikisha miezi kumi na miwili.","source":"generated"}],"synonyms_dg":[],"antonyms_dg":[],"cross_refs":[],"cultural_note":null,"register":"neutral","dialect_tags":[]},{"sense_id":2,"definition_en":"to prevent, not to allow someone do something","definition_sw":"kukataza","definition_dg":"Kuzuwiya mutu asihende chitu, kukataza.","definition_dg_status":"draft","examples":[{"dg":"Baba wamziza mwanawe asiphiye kuko.","en":"Father prevented his child from going there.","sw":"Baba alimkataza mtoto wake asiende huko.","source":"generated"}],"synonyms_dg":[],"antonyms_dg":[],"cross_refs":[],"cultural_note":null,"register":"neutral","dialect_tags":[]}],"etymology":{"source":null,"root":null,"notes":""},"bible_refs":[],"proverb_refs":[],"sub_entries":[],"editorial_state":"draft","is_redirect":false,"redirect_target":null},{"id":"zizima","headword":"zizima","homonym_index":null,"sort_key":"zizima","pos":"chihendo","pos_en":"verb","noun_class":null,"plural_prefix":null,"plural_form":null,"ipa":"/zizima/","audio":[],"equivalents_en":["be wet or cold"],"equivalents_sw":["kuzizima"],"variants":[],"senses":[{"sense_id":1,"definition_en":"to be wet or cold","definition_sw":"kuzizima","definition_dg":"Kukala na utsu-utsu au baridi.","definition_dg_status":"draft","examples":[{"dg":"Nguwo inazizima","en":"The cloth is wet","sw":"Nguo inazizima, bado haijakauka.","source":"mgombato"}],"synonyms_dg":[],"antonyms_dg":[],"cross_refs":[],"cultural_note":null,"register":"neutral","dialect_tags":[]}],"etymology":{"source":null,"root":null,"notes":""},"bible_refs":[],"proverb_refs":[],"sub_entries":[],"editorial_state":"draft","is_redirect":false,"redirect_target":null},{"id":"zizimisa","headword":"zizimisa","homonym_index":null,"sort_key":"zizimisa","pos":"chihendo","pos_en":"verb","noun_class":null,"plural_prefix":null,"plural_form":null,"ipa":"/zizimisa/","audio":[],"equivalents_en":["cool something down"],"equivalents_sw":["kuzizimisha"],"variants":[],"senses":[{"sense_id":1,"definition_en":"to cool something down","definition_sw":"kuzizimisha","definition_dg":"Kuhendesa chitu chipoe au chikale na baridi.","definition_dg_status":"draft","examples":[{"dg":"Zizimisa mchuzi kabila ya kuumimina.","en":"Cool down the stew before pouring it.","sw":"Poza mchuzi kabla ya kuumimina.","source":"generated"}],"synonyms_dg":[],"antonyms_dg":[],"cross_refs":[],"cultural_note":null,"register":"neutral","dialect_tags":[]}],"etymology":{"source":null,"root":null,"notes":""},"bible_refs":[],"proverb_refs":[],"sub_entries":[],"editorial_state":"draft","is_redirect":false,"redirect_target":null},{"id":"zo","headword":"zo","homonym_index":null,"sort_key":"zo","pos":"dzina","pos_en":"noun","noun_class":null,"plural_prefix":null,"plural_form":null,"ipa":"/zɔ/","audio":[],"equivalents_en":["noun class 10 equivalent of cho"],"equivalents_sw":["zile; ambazo (angalia cho)"],"variants":[],"senses":[{"sense_id":1,"definition_en":"noun class 10 equivalent of cho","definition_sw":"zile; ambazo (angalia cho)","definition_dg":"Neno ra kisarufi ra darasa ra 10 rinalolingana na cho.","definition_dg_status":"draft","examples":[{"dg":"Nguwo zo ni ndzuri sana.","en":"Those clothes are very beautiful.","sw":"Nguo zile ni nzuri sana.","source":"generated"}],"synonyms_dg":[],"antonyms_dg":[],"cross_refs":[],"cultural_note":null,"register":"neutral","dialect_tags":[]}],"etymology":{"source":null,"root":null,"notes":""},"bible_refs":[],"proverb_refs":[],"sub_entries":[],"editorial_state":"draft","is_redirect":false,"redirect_target":null},{"id":"zobe","headword":"zobe","homonym_index":null,"sort_key":"zobe","pos":"dzina","pos_en":"noun","noun_class":null,"plural_prefix":"ma","plural_form":null,"ipa":"/zɔbɛ/","audio":[],"equivalents_en":["edible crab"],"equivalents_sw":["kaa"],"variants":[],"senses":[{"sense_id":1,"definition_en":"edible crab","definition_sw":"kaa","definition_dg":"Nyama wa baharina mwenye ganda gumu ambaye anarwa na binadamu, kaa.","definition_dg_status":"draft","examples":[{"dg":"Wavuvi agbwira mazobe baharina.","en":"The fishermen caught crabs from the sea.","sw":"Wavuvi walivua kaa baharini.","source":"generated"}],"synonyms_dg":[],"antonyms_dg":[],"cross_refs":[],"cultural_note":null,"register":"neutral","dialect_tags":[]}],"etymology":{"source":null,"root":null,"notes":""},"bible_refs":[],"proverb_refs":[],"sub_entries":[],"editorial_state":"draft","is_redirect":false,"redirect_target":null},{"id":"zola","headword":"zola","homonym_index":null,"sort_key":"zola","pos":"chihendo","pos_en":"verb","noun_class":null,"plural_prefix":null,"plural_form":null,"ipa":"/zɔla/","audio":[],"equivalents_en":["run","to chase away"],"equivalents_sw":["kukimbia","kufukuza"],"variants":[],"senses":[{"sense_id":1,"definition_en":"to run, to chase away","definition_sw":"kukimbia, kufukuza","definition_dg":"Kukimbiira, au kufukuza mutu.","definition_dg_status":"draft","examples":[{"dg":"Zola ng'ombe kula mundani!","en":"Chase the cattle from the farm!","sw":"Fukuza ng'ombe kutoka shambani!","source":"generated"}],"synonyms_dg":[],"antonyms_dg":[],"cross_refs":[],"cultural_note":null,"register":"neutral","dialect_tags":[]}],"etymology":{"source":null,"root":null,"notes":""},"bible_refs":[],"proverb_refs":[],"sub_entries":[],"editorial_state":"draft","is_redirect":false,"redirect_target":null},{"id":"zondoha","headword":"zondoha","homonym_index":null,"sort_key":"zondoha","pos":"chihendo","pos_en":"verb","noun_class":null,"plural_prefix":null,"plural_form":null,"ipa":"/zɔⁿdɔha/","audio":[],"equivalents_en":["shuffle on one's bottom or backside"],"equivalents_sw":["kutambaa kwa matako"],"variants":[],"senses":[{"sense_id":1,"definition_en":"to shuffle on one's bottom or backside","definition_sw":"kutambaa kwa matako","definition_dg":"Kutambaa kpwa matako, hasa anache.","definition_dg_status":"draft","examples":[{"dg":"Mwanache mdide anazondoha badala ya kutembea.","en":"The baby shuffles on his bottom instead of walking.","sw":"Mtoto mdogo anatambaa kwa matako badala ya kutembea.","source":"generated"}],"synonyms_dg":[],"antonyms_dg":[],"cross_refs":[],"cultural_note":null,"register":"neutral","dialect_tags":[]},{"sense_id":2,"definition_en":"to be involved in witchcraft (utsai)","definition_sw":"kufanya mambo ya uchawi (utsai)","definition_dg":"Kuhenda mambo ya uchawi.","definition_dg_status":"draft","examples":[{"dg":"Mutu yuya anaambiwa anazondoha.","en":"That person is said to be involved in witchcraft.","sw":"Mtu yule inasemekana anafanya uchawi.","source":"generated"}],"synonyms_dg":[],"antonyms_dg":[],"cross_refs":[],"cultural_note":null,"register":"neutral","dialect_tags":[]}],"etymology":{"source":null,"root":null,"notes":""},"bible_refs":[],"proverb_refs":[],"sub_entries":[],"editorial_state":"draft","is_redirect":false,"redirect_target":null},{"id":"zorera","headword":"zorera","homonym_index":null,"sort_key":"zorera","pos":"chihendo","pos_en":"verb","noun_class":null,"plural_prefix":null,"plural_form":null,"ipa":"/zɔrɛra/","audio":[],"equivalents_en":["run after","to pursue"],"equivalents_sw":["kukimbia"],"variants":[],"senses":[{"sense_id":1,"definition_en":"to run after, to pursue","definition_sw":"kukimbia","definition_dg":"Kuzola mutu, kumzolera.","definition_dg_status":"draft","examples":[{"dg":"Mwivi wazorerwa ni atu hadi akagbwirwa.","en":"The thief was chased by people until he was caught.","sw":"Mwizi alifukuzwa na watu hadi akashikwa.","source":"generated"}],"synonyms_dg":[],"antonyms_dg":[],"cross_refs":[],"cultural_note":null,"register":"neutral","dialect_tags":[]}],"etymology":{"source":null,"root":null,"notes":""},"bible_refs":[],"proverb_refs":[],"sub_entries":[],"editorial_state":"draft","is_redirect":false,"redirect_target":null},{"id":"zoresa","headword":"zoresa","homonym_index":null,"sort_key":"zoresa","pos":"chihendo","pos_en":"verb","noun_class":null,"plural_prefix":null,"plural_form":null,"ipa":"/zɔrɛsa/","audio":[],"equivalents_en":["chase away","to chase after"],"equivalents_sw":["kufukuza"],"variants":[],"senses":[{"sense_id":1,"definition_en":"to chase away, to chase after","definition_sw":"kufukuza","definition_dg":"Kufukuza mutu au nyama, kumzoresa.","definition_dg_status":"draft","examples":[{"dg":"Zoresa kuku kula mundani!","en":"Chase away the chickens from the farm!","sw":"Fukuza kuku kutoka shambani!","source":"generated"}],"synonyms_dg":[],"antonyms_dg":[],"cross_refs":[],"cultural_note":null,"register":"neutral","dialect_tags":[]}],"etymology":{"source":null,"root":null,"notes":""},"bible_refs":[],"proverb_refs":[],"sub_entries":[],"editorial_state":"draft","is_redirect":false,"redirect_target":null},{"id":"zuga-zuga","headword":"zuga-zuga","homonym_index":null,"sort_key":"zuga-zuga","pos":"chihendo","pos_en":"verb","noun_class":null,"plural_prefix":null,"plural_form":null,"ipa":"/zuɡa-zuɡa/","audio":[],"equivalents_en":["be unsteady","to sway","to stagger"],"equivalents_sw":["kuyumba"],"variants":[],"senses":[{"sense_id":1,"definition_en":"to be unsteady, to sway, to stagger","definition_sw":"kuyumba","definition_dg":"Kutokuwa imara, kuyumba, kutikisika.","definition_dg_status":"draft","examples":[{"dg":"Meza inazuga-zuga kpwa sababu mgulu mmwenga umevundzika.","en":"The table is unsteady because one leg is broken.","sw":"Meza inatikisika kwa sababu mguu mmoja umevunjika.","source":"generated"}],"synonyms_dg":[],"antonyms_dg":[],"cross_refs":[],"cultural_note":null,"register":"neutral","dialect_tags":[]}],"etymology":{"source":null,"root":null,"notes":""},"bible_refs":[],"proverb_refs":[],"sub_entries":[],"editorial_state":"draft","is_redirect":false,"redirect_target":null},{"id":"zuguza","headword":"zuguza","homonym_index":null,"sort_key":"zuguza","pos":"chihendo","pos_en":"verb","noun_class":null,"plural_prefix":null,"plural_form":null,"ipa":"/zuɡuza/","audio":[],"equivalents_en":["shake"],"equivalents_sw":["kutingisha"],"variants":[],"senses":[{"sense_id":1,"definition_en":"to shake","definition_sw":"kutingisha","definition_dg":"Kutingisha chitu hiku na hiku.","definition_dg_status":"draft","examples":[{"dg":"Usizuguze meza, vitu vindagbwa.","en":"Don't shake the table, things will fall.","sw":"Usitingishe meza, vitu vitaanguka.","source":"generated"}],"synonyms_dg":[],"antonyms_dg":[],"cross_refs":[],"cultural_note":null,"register":"neutral","dialect_tags":[]}],"etymology":{"source":null,"root":null,"notes":""},"bible_refs":[],"proverb_refs":[],"sub_entries":[],"editorial_state":"draft","is_redirect":false,"redirect_target":null},{"id":"zuka.1","headword":"zuka","homonym_index":1,"sort_key":"zuka","pos":"dzina","pos_en":"noun","noun_class":null,"plural_prefix":null,"plural_form":null,"ipa":"/zuka/","audio":[],"equivalents_en":["won't fall will be shaken down (e.g. fruits from a tree)"],"equivalents_sw":[],"variants":[],"senses":[{"sense_id":1,"definition_en":"won't fall will be shaken down (e.g. fruits from a tree)","definition_sw":"","definition_dg":"Kutingishwa na kugbwa photsi, dza matunda kula muhini.","definition_dg_status":"draft","examples":[{"dg":"Matunda ga muembe ganazuka gachitingishwa.","en":"The mango fruits fall when shaken down.","sw":"Matunda ya muembe yanaanguka yakitingishwa.","source":"generated"}],"synonyms_dg":[],"antonyms_dg":[],"cross_refs":["dindirisa.1","kutisa","suka.1","sumba.1"],"cultural_note":null,"register":"neutral","dialect_tags":[]}],"etymology":{"source":null,"root":null,"notes":""},"bible_refs":[],"proverb_refs":[],"sub_entries":[],"editorial_state":"draft","is_redirect":false,"redirect_target":null},{"id":"zuka.2","headword":"zuka","homonym_index":2,"sort_key":"zuka","pos":"chihendo","pos_en":"verb","noun_class":null,"plural_prefix":null,"plural_form":null,"ipa":"/zuka/","audio":[],"equivalents_en":["stand up","to appear suddenly"],"equivalents_sw":["kuinuka","kutokea kwa ghafula"],"variants":[],"senses":[{"sense_id":1,"definition_en":"to stand up, to appear suddenly","definition_sw":"kuinuka, kutokea kwa ghafula","definition_dg":"Kusimama kpwa ghafula, kutokea.","definition_dg_status":"draft","examples":[{"dg":"Wazuka na kuima haraka sana.","en":"He stood up suddenly.","sw":"Aliinuka na kusimama haraka sana.","source":"generated"}],"synonyms_dg":[],"antonyms_dg":[],"cross_refs":[],"cultural_note":null,"register":"neutral","dialect_tags":[]}],"etymology":{"source":null,"root":null,"notes":""},"bible_refs":[],"proverb_refs":[],"sub_entries":[],"editorial_state":"draft","is_redirect":false,"redirect_target":null},{"id":"zula","headword":"zula","homonym_index":null,"sort_key":"zula","pos":"chihendo","pos_en":"verb","noun_class":null,"plural_prefix":null,"plural_form":null,"ipa":"/zula/","audio":[],"equivalents_en":["dig up a hidden charm (see zuza)"],"equivalents_sw":["kung'oa vitu vilivyozikwa kichawi (angalia zuza)"],"variants":[],"senses":[{"sense_id":1,"definition_en":"to dig up a hidden charm (see zuza)","definition_sw":"kung'oa vitu vilivyozikwa kichawi (angalia zuza)","definition_dg":"Kungʼoa hirizi au dawa za uchawi ambazo zikazikpwa kpwenye tsongo.","definition_dg_status":"draft","examples":[{"dg":"Mganga wazula dawa za uchawi kula tsongoni.","en":"The healer dug up the witchcraft charm from the ground.","sw":"Mganga alingʼoa dawa za uchawi kutoka ardhini.","source":"generated"}],"synonyms_dg":[],"antonyms_dg":[],"cross_refs":[],"cultural_note":null,"register":"neutral","dialect_tags":[]}],"etymology":{"source":null,"root":null,"notes":""},"bible_refs":[],"proverb_refs":[],"sub_entries":[],"editorial_state":"draft","is_redirect":false,"redirect_target":null},{"id":"zulumu","headword":"zulumu","homonym_index":null,"sort_key":"zulumu","pos":"chihendo","pos_en":"verb","noun_class":null,"plural_prefix":null,"plural_form":null,"ipa":"/zulumu/","audio":[],"equivalents_en":["opress","to treat unjustly"],"equivalents_sw":["kudhulumu"],"variants":[],"senses":[{"sense_id":1,"definition_en":"to opress, to treat unjustly","definition_sw":"kudhulumu","definition_dg":"Kumtendere mutu vibaya, kumuonera, kudhulumu.","definition_dg_status":"draft","examples":[{"dg":"Usimzulumu mutu asiye na makosa.","en":"Don't oppress an innocent person.","sw":"Usimdhulumu mtu asiye na makosa.","source":"generated"}],"synonyms_dg":[],"antonyms_dg":[],"cross_refs":[],"cultural_note":null,"register":"neutral","dialect_tags":[]}],"etymology":{"source":null,"root":null,"notes":""},"bible_refs":[],"proverb_refs":[],"sub_entries":[],"editorial_state":"draft","is_redirect":false,"redirect_target":null},{"id":"zuma","headword":"zuma","homonym_index":null,"sort_key":"zuma","pos":"dzina","pos_en":"noun","noun_class":null,"plural_prefix":"ma","plural_form":null,"ipa":"/zuma/","audio":[],"equivalents_en":["turn","shift"],"equivalents_sw":["zamu"],"variants":[],"senses":[{"sense_id":1,"definition_en":"turn, shift","definition_sw":"zamu","definition_dg":"Zamu, wakati wa mutu kuhenda chitu.","definition_dg_status":"draft","examples":[{"dg":"Rero ni zuma rangu ra kujita","en":"Today it is my turn to cook","sw":"Leo ni zamu yangu ya kupika.","source":"mgombato"},{"dg":"Kala anaimba mazuma kuphokezana na yuya ariyekala dibwani","en":"He was singing in turns, taking turns with with whoever was in the pit","sw":"Leo ni zamu yangu ya kupika.","source":"mgombato"}],"synonyms_dg":[],"antonyms_dg":[],"cross_refs":[],"cultural_note":null,"register":"neutral","dialect_tags":[]}],"etymology":{"source":null,"root":null,"notes":""},"bible_refs":[],"proverb_refs":[],"sub_entries":[],"editorial_state":"draft","is_redirect":false,"redirect_target":null},{"id":"zumi","headword":"zumi","homonym_index":null,"sort_key":"zumi","pos":"dzina","pos_en":"noun","noun_class":null,"plural_prefix":"-","plural_form":null,"ipa":"/zumi/","audio":[],"equivalents_en":["loud singing in a big group walking or dancing"],"equivalents_sw":["sauti zinazosikika watu wanapoimba"],"variants":[],"senses":[{"sense_id":1,"definition_en":"loud singing in a big group walking or dancing","definition_sw":"sauti zinazosikika watu wanapoimba","definition_dg":"Kuimba kpwa sauti kulu kpwa kundi ra atu arikoenenda au kuteza.","definition_dg_status":"draft","examples":[{"dg":"Atu apiga zumi ariphokala anaenenda.","en":"People sang loudly as they were walking.","sw":"Watu waliimba kwa sauti kubwa walipokuwa wanatembea.","source":"generated"}],"synonyms_dg":[],"antonyms_dg":[],"cross_refs":[],"cultural_note":null,"register":"neutral","dialect_tags":[]}],"etymology":{"source":null,"root":null,"notes":""},"bible_refs":[],"proverb_refs":[],"sub_entries":[],"editorial_state":"draft","is_redirect":false,"redirect_target":null},{"id":"zumo","headword":"zumo","homonym_index":null,"sort_key":"zumo","pos":"dzina","pos_en":"noun","noun_class":null,"plural_prefix":"-","plural_form":null,"ipa":"/zumɔ/","audio":[],"equivalents_en":["singing in unison"],"equivalents_sw":["kuimba kwa pamoja"],"variants":[],"senses":[{"sense_id":1,"definition_en":"singing in unison","definition_sw":"kuimba kwa pamoja","definition_dg":"Kuimba kpwa phamwenga, kpwa sauti mwenga.","definition_dg_status":"draft","examples":[{"dg":"Atu aimba zumo kpwenye sherehe.","en":"People sang in unison at the celebration.","sw":"Watu waliimba kwa pamoja kwenye sherehe.","source":"generated"}],"synonyms_dg":[],"antonyms_dg":[],"cross_refs":[],"cultural_note":null,"register":"neutral","dialect_tags":[]}],"etymology":{"source":null,"root":null,"notes":""},"bible_refs":[],"proverb_refs":[],"sub_entries":[],"editorial_state":"draft","is_redirect":false,"redirect_target":null},{"id":"zunguluka","headword":"zunguluka","homonym_index":null,"sort_key":"zunguluka","pos":"chihendo","pos_en":"verb","noun_class":null,"plural_prefix":null,"plural_form":null,"ipa":"/zuᵑɡuluka/","audio":[],"equivalents_en":["go about everywhere","to wander"],"equivalents_sw":["go round","to surround; kuzunguka"],"variants":[],"senses":[{"sense_id":1,"definition_en":"to go about everywhere, to wander","definition_sw":"to go round, to surround; kuzunguka","definition_dg":"Kuphiya hiku na hiku, kuzunguka.","definition_dg_status":"draft","examples":[{"dg":"Wazunguluka mudzi wosi achitafuta kazi.","en":"He went around the whole village looking for work.","sw":"Alizunguka kijiji chote akitafuta kazi.","source":"generated"}],"synonyms_dg":[],"antonyms_dg":[],"cross_refs":[],"cultural_note":null,"register":"neutral","dialect_tags":[]}],"etymology":{"source":null,"root":null,"notes":""},"bible_refs":[],"proverb_refs":[],"sub_entries":[],"editorial_state":"draft","is_redirect":false,"redirect_target":null},{"id":"zungulusa","headword":"zungulusa","homonym_index":null,"sort_key":"zungulusa","pos":"chihendo","pos_en":"verb","noun_class":null,"plural_prefix":null,"plural_form":null,"ipa":"/zuᵑɡulusa/","audio":[],"equivalents_en":["turn something around","to rotate"],"equivalents_sw":["kuzungusha"],"variants":[],"senses":[{"sense_id":1,"definition_en":"to turn something around, to rotate","definition_sw":"kuzungusha","definition_dg":"Kuzungusha chitu, kuhendesa chitu chizunguke.","definition_dg_status":"draft","examples":[{"dg":"Zungulusa gurudumu ili gari iphiye.","en":"Turn the wheel so the car moves.","sw":"Zungusha gurudumu ili gari liende.","source":"generated"}],"synonyms_dg":[],"antonyms_dg":[],"cross_refs":[],"cultural_note":null,"register":"neutral","dialect_tags":[]},{"sense_id":2,"definition_en":"to show","definition_sw":"","definition_dg":"Kuonyesa mutu phatu.","definition_dg_status":"draft","examples":[{"dg":"Wamzungulusa mjeni mudzi wosi.","en":"He showed the visitor around the whole village.","sw":"Alimzungusha mgeni kijiji chote.","source":"generated"}],"synonyms_dg":[],"antonyms_dg":[],"cross_refs":[],"cultural_note":null,"register":"neutral","dialect_tags":[]}],"etymology":{"source":null,"root":null,"notes":""},"bible_refs":[],"proverb_refs":[],"sub_entries":[{"id":"zungulusa/people","form":"people","pos":null,"pos_en":null,"definition_en":"around","definition_sw":"kuzungusha watu, kutembeza watu","definition_dg":"","definition_dg_status":"pending","definition_dg_source":null,"examples":[{"dg":"3) to enclose e.g","en":"a","sw":"","source":"mgombato"}],"register":"neutral","dialect_tags":[],"editorial_state":"draft"},{"id":"zungulusa/piece_of","form":"piece of","pos":null,"pos_en":null,"definition_en":"land by erecting a boundary around it","definition_sw":"kuzungusha kiwanja kabisa","definition_dg":"","definition_dg_status":"pending","definition_dg_source":null,"examples":[],"register":"neutral","dialect_tags":[],"editorial_state":"draft"}],"editorial_state":"draft","is_redirect":false,"redirect_target":null},{"id":"zungurusa","headword":"zungurusa","homonym_index":null,"sort_key":"zungurusa","pos":"chihendo","pos_en":"verb","noun_class":null,"plural_prefix":null,"plural_form":null,"ipa":"","audio":[],"equivalents_en":[],"equivalents_sw":[],"variants":[],"senses":[],"etymology":{"source":null,"root":null,"notes":""},"bible_refs":[],"proverb_refs":[],"sub_entries":[],"editorial_state":"draft","is_redirect":true,"redirect_target":"zungulusa;"},{"id":"zuri","headword":"-zuri","homonym_index":null,"sort_key":"zuri","pos":"sifa","pos_en":"adjective","noun_class":null,"plural_prefix":null,"plural_form":null,"ipa":"/zuri/","audio":[],"equivalents_en":["good","beautiful","nice"],"equivalents_sw":["zuri"],"variants":[],"senses":[{"sense_id":1,"definition_en":"good, beautiful, nice","definition_sw":"zuri","definition_dg":"Chenye kupendeza, chinono, chirembo.","definition_dg_status":"draft","examples":[{"dg":"Nyumba hino ni ndzuri sana.","en":"This house is very beautiful.","sw":"Nyumba hii ni nzuri sana.","source":"generated"}],"synonyms_dg":[],"antonyms_dg":[],"cross_refs":[],"cultural_note":null,"register":"neutral","dialect_tags":[]}],"etymology":{"source":null,"root":null,"notes":""},"bible_refs":[],"proverb_refs":[],"sub_entries":[],"editorial_state":"draft","is_redirect":false,"redirect_target":null},{"id":"zurura","headword":"zurura","homonym_index":null,"sort_key":"zurura","pos":"chihendo","pos_en":"verb","noun_class":null,"plural_prefix":null,"plural_form":null,"ipa":"/zurura/","audio":[],"equivalents_en":["wander around"],"equivalents_sw":["kuzunguluka"],"variants":[],"senses":[{"sense_id":1,"definition_en":"to wander around","definition_sw":"kuzunguluka","definition_dg":"Kuzunguka-zunguka bila lengo, kutembea ovyo.","definition_dg_status":"draft","examples":[{"dg":"Ni dambi kpwa Mlungu kuzurura bila ya kazi na dziloni unataka kurya","en":"It is a sin against God to wander around without work and then expect to eat in the evening","sw":"Ni dhambi kuzurura bila kazi na jioni unataka kula.","source":"mgombato"}],"synonyms_dg":[],"antonyms_dg":[],"cross_refs":[],"cultural_note":null,"register":"neutral","dialect_tags":[]}],"etymology":{"source":null,"root":null,"notes":""},"bible_refs":[],"proverb_refs":[],"sub_entries":[],"editorial_state":"draft","is_redirect":false,"redirect_target":null},{"id":"zuwiya.1","headword":"zuwiya","homonym_index":1,"sort_key":"zuwiya","pos":"dzina","pos_en":"noun","noun_class":null,"plural_prefix":null,"plural_form":null,"ipa":"/zuwija/","audio":[],"equivalents_en":["kind of dance"],"equivalents_sw":["aina ya ngoma"],"variants":[],"senses":[{"sense_id":1,"definition_en":"kind of dance","definition_sw":"aina ya ngoma","definition_dg":"Aina ya machezo ga chijadi.","definition_dg_status":"draft","examples":[{"dg":"Atu ateza zuwiya kpwenye sherehe ya chijadi.","en":"People performed the zuwiya dance at the traditional ceremony.","sw":"Watu walicheza zuwiya kwenye sherehe ya kimila.","source":"generated"}],"synonyms_dg":[],"antonyms_dg":[],"cross_refs":[],"cultural_note":null,"register":"neutral","dialect_tags":[]}],"etymology":{"source":null,"root":null,"notes":""},"bible_refs":[],"proverb_refs":[],"sub_entries":[],"editorial_state":"draft","is_redirect":false,"redirect_target":null},{"id":"zuwiya.2","headword":"zuwiya","homonym_index":2,"sort_key":"zuwiya","pos":"chihendo","pos_en":"verb","noun_class":null,"plural_prefix":null,"plural_form":null,"ipa":"/zuwija/","audio":[],"equivalents_en":["block","to prevent"],"equivalents_sw":["kuzuia"],"variants":[],"senses":[{"sense_id":1,"definition_en":"to block, to prevent","definition_sw":"kuzuia","definition_dg":"Kuzuwiya, kuzuia mutu au chitu.","definition_dg_status":"draft","examples":[{"dg":"Zuwiya mwanache asiphiye kpwenye hatari.","en":"Prevent the child from going into danger.","sw":"Zuia mtoto asiende kwenye hatari.","source":"generated"}],"synonyms_dg":[],"antonyms_dg":[],"cross_refs":[],"cultural_note":null,"register":"neutral","dialect_tags":[]}],"etymology":{"source":null,"root":null,"notes":""},"bible_refs":[],"proverb_refs":[],"sub_entries":[],"editorial_state":"draft","is_redirect":false,"redirect_target":null},{"id":"zuza","headword":"zuza","homonym_index":null,"sort_key":"zuza","pos":"chihendo","pos_en":"verb","noun_class":null,"plural_prefix":null,"plural_form":null,"ipa":"/zuza/","audio":[],"equivalents_en":["remove something evil"],"equivalents_sw":[],"variants":[],"senses":[{"sense_id":1,"definition_en":"to remove something evil, usually due to witchcraft (utsai) using a","definition_sw":"","definition_dg":"Kuusa chitu kibaya, haswa cha uchawi, kpwa kuisafisha phatu.","definition_dg_status":"draft","examples":[{"dg":"Mganga wazuza nyumba yosi kpwa kuisafisha.","en":"The healer cleansed the whole house by removing evil charms.","sw":"Mganga alisafisha nyumba yote kwa kuondoa uchawi.","source":"generated"}],"synonyms_dg":[],"antonyms_dg":[],"cross_refs":[],"cultural_note":null,"register":"neutral","dialect_tags":[]}],"etymology":{"source":null,"root":null,"notes":""},"bible_refs":[],"proverb_refs":[],"sub_entries":[{"id":"zuza/specific","form":"specific","pos":null,"pos_en":null,"definition_en":"object","definition_sw":"kuondoa kitu kibaya kilicholetwa na uchawi (utsai)","definition_dg":"","definition_dg_status":"pending","definition_dg_source":null,"examples":[],"register":"neutral","dialect_tags":[],"editorial_state":"draft"}],"editorial_state":"draft","is_redirect":false,"redirect_target":null},{"id":"zuzu","headword":"-zuzu","homonym_index":null,"sort_key":"zuzu","pos":"sifa","pos_en":"adjective","noun_class":null,"plural_prefix":null,"plural_form":null,"ipa":"/zuzu/","audio":[],"equivalents_en":["stupid","foolish"],"equivalents_sw":["mzuzu"],"variants":[],"senses":[{"sense_id":1,"definition_en":"stupid, foolish","definition_sw":"mzuzu","definition_dg":"Wa kijinga, asiye na achili, -zuzu.","definition_dg_status":"draft","examples":[{"dg":"Usikale mzuzu, humira achilizo.","en":"Don't be foolish, use your brain.","sw":"Usiwe mzuzu, tumia akili yako.","source":"generated"}],"synonyms_dg":[],"antonyms_dg":[],"cross_refs":[],"cultural_note":null,"register":"neutral","dialect_tags":[]}],"etymology":{"source":null,"root":null,"notes":""},"bible_refs":[],"proverb_refs":[],"sub_entries":[],"editorial_state":"draft","is_redirect":false,"redirect_target":null}]}